edc_csf/__init__.py
edc_csf/admin.py
edc_csf/admin_site.py
edc_csf/aliquot_types.py
edc_csf/apps.py
edc_csf/auth_objects.py
edc_csf/auths.py
edc_csf/choices.py
edc_csf/fieldsets.py
edc_csf/form_validators.py
edc_csf/forms.py
edc_csf/migrations/0001_initial.py
edc_csf/migrations/0002_auto_20220225_0419.py
edc_csf/migrations/0003_auto_20220225_0423.py
edc_csf/migrations/0004_auto_20220225_0500.py
edc_csf/migrations/0005_auto_20220225_2142.py
edc_csf/migrations/0006_auto_20220228_2032.py
edc_csf/migrations/0007_auto_20220711_1230.py
edc_csf/migrations/0008_alter_historicallpcsf_csf_amount_removed_and_more.py
edc_csf/migrations/0009_alter_lpcsf_options_alter_lpcsf_managers_and_more.py
edc_csf/migrations/0010_alter_lpcsf_options_historicallpcsf_locale_created_and_more.py
edc_csf/migrations/0011_alter_historicallpcsf_site_alter_lpcsf_site.py
edc_csf/migrations/0012_alter_historicallpcsf_revision_alter_lpcsf_revision.py
edc_csf/migrations/0013_alter_historicallpcsf_created_and_more.py
edc_csf/migrations/0014_alter_historicallpcsf_device_created_and_more.py
edc_csf/migrations/0015_alter_historicallpcsf_device_created_and_more.py
edc_csf/migrations/0016_alter_historicallpcsf_csf_crag_and_more.py
edc_csf/migrations/__init__.py
edc_csf/model_mixins/__init__.py
edc_csf/model_mixins/biosynex_semi_quantitative_crag_mixin.py
edc_csf/model_mixins/csf.py
edc_csf/model_mixins/csf_culture.py
edc_csf/model_mixins/lp.py
edc_csf/model_mixins/quantitative_culture.py
edc_csf/modeladmin_mixins.py
edc_csf/models.py
edc_csf/panels.py
edc_csf/processing_profiles.py
edc_csf/urls.py
edc_csf-1.3.0.dist-info/licenses/LICENSE
edc_csf-1.3.0.dist-info/WHEEL
edc_csf-1.3.0.dist-info/METADATA
edc_csf-1.3.0.dist-info/RECORD
